ibis_extensions/__init__.py
ibis_extensions/dedup.py
ibis_extensions/dummies.py
ibis_extensions/pivot.py
ibis_extensions/tests/__init__.py
ibis_extensions/tests/test_dedup.py
ibis_extensions/tests/test_dummies.py
ibis_extensions/tests/test_pivot.py
ibis_extensions/tests/test_timeseries.py
ibis_extensions/time_series.py
ibis_extensions-0.1.2.dist-info/LICENSE
ibis_extensions-0.1.2.dist-info/WHEEL
ibis_extensions-0.1.2.dist-info/METADATA
ibis_extensions-0.1.2.dist-info/RECORD
